comtradeapicall/Async.py
comtradeapicall/BulkDownload.py
comtradeapicall/DataAvailability.py
comtradeapicall/Metadata.py
comtradeapicall/PreviewGet.py
comtradeapicall/SUV.py
comtradeapicall/__init__.py
comtradeapicall-1.3.0.dist-info/licenses/LICENSE
comtradeapicall-1.3.0.dist-info/METADATA
comtradeapicall-1.3.0.dist-info/PKG-INFO-W10LT-PF2ZCSNL
comtradeapicall-1.3.0.dist-info/WHEEL
comtradeapicall-1.3.0.dist-info/top_level.txt
comtradeapicall-1.3.0.dist-info/RECORD
