Metadata-Version: 2.4
Name: comtradeapicall
Version: 1.3.0
Summary: A package to call UN Comtrade APIs
Author-email: untradestats <untradestats@gmail.com>
Project-URL: Homepage, https://github.com/uncomtrade/comtradeapicall
Project-URL: Bug Tracker, https://github.com/uncomtrade/comtradeapicall/issues
Classifier: Programming Language :: Python :: 3
Classifier: License :: OSI Approved :: MIT License
Classifier: Operating System :: OS Independent
Requires-Python: >=3.7
License-File: LICENSE
Dynamic: license-file
